README.rst
setup.py
bin/pyipa_dist
pyipa_dist/HTMLMaker.py
pyipa_dist/PlistMaker.py
pyipa_dist/__init__.py
pyipa_dist.egg-info/PKG-INFO
pyipa_dist.egg-info/SOURCES.txt
pyipa_dist.egg-info/dependency_links.txt
pyipa_dist.egg-info/requires.txt
pyipa_dist.egg-info/top_level.txt