Metadata-Version: 1.1
Name: pyipa-dist
Version: 1.0.3
Summary: This python module to creates plist, html file for Adhoc distribution
Home-page: https://github.com/hoiogi/pyipa_dist
Author: ChangWook Jeong
Author-email: hoiogi@gmail.com
License: MIT
Download-URL: https://github.com/hoiogi/pyipa_dist/tarball/1.0.3
Keywords: pyipa,dist,distribution,adhoc,ipa
Platform: UNKNOWN
